{
	"animations": [
		{
			"offsets": [
				0,
				0
			],
			"loop": false,
			"fps": 24,
			"anim": "firstDeath",
			"indices": [],
			"name": "cursed dead loop"
		},
		{
			"offsets": [
				0,
				0
			],
			"loop": false,
			"fps": 24,
			"anim": "deathLoop",
			"indices": [],
			"name": "cursed dead loop"
		},
		{
			"offsets": [
				50,
				42
			],
			"loop": false,
			"fps": 24,
			"anim": "deathConfirm",
			"indices": [],
			"name": "cursed dead confirm"
		}
	],
	"no_antialiasing": false,
	"image": "characters/CURSEDRETRY",
	"position": [
		0,
		0
	],
	"healthicon": "nikku",
	"flip_x": true,
	"healthbar_colors": [
		178,
		14,
		54
	],
	"camera_position": [
		0,
		0
	],
	"sing_duration": 6.1,
	"scale": 1.2
}